trafficserver_exporter/__init__.py
trafficserver_exporter/__main__.py
trafficserver_exporter/collector.py
trafficserver_exporter/http.py
trafficserver_exporter/metrics.yaml
trafficserver_exporter/trafficserver_exporter.py
trafficserver_exporter-0.4.0.dist-info/LICENSE
trafficserver_exporter-0.4.0.dist-info/METADATA
trafficserver_exporter-0.4.0.dist-info/WHEEL
trafficserver_exporter-0.4.0.dist-info/entry_points.txt
trafficserver_exporter-0.4.0.dist-info/top_level.txt
trafficserver_exporter-0.4.0.dist-info/RECORD
